computer_mcp/__init__.py
computer_mcp/__main__.py
computer_mcp/api.py
computer_mcp/cli.py
computer_mcp/main.py
computer_mcp/mcp.py
computer_mcp/server.py
computer_mcp/actions/__init__.py
computer_mcp/actions/accessibility_tree.py
computer_mcp/actions/config.py
computer_mcp/actions/focused_app.py
computer_mcp/actions/keyboard.py
computer_mcp/actions/mouse.py
computer_mcp/actions/screenshot.py
computer_mcp/actions/terminal.py
computer_mcp/actions/window.py
computer_mcp/core/__init__.py
computer_mcp/core/platform.py
computer_mcp/core/response.py
computer_mcp/core/screenshot.py
computer_mcp/core/state.py
computer_mcp/core/system_metrics.py
computer_mcp/core/utils.py
computer_mcp/core/virtual_desktop.py
computer_mcp/handlers/__init__.py
computer_mcp/handlers/accessibility_tree.py
computer_mcp/handlers/config.py
computer_mcp/handlers/focused_app.py
computer_mcp/handlers/keyboard.py
computer_mcp/handlers/mouse.py
computer_mcp/handlers/screenshot.py
computer_mcp/handlers/terminal.py
computer_mcp/handlers/window.py
computer_mcp/resources/VirtualDesktopAccessor.dll
computer_mcp/resources/__init__.py
computer_mcp-0.0.7.dist-info/licenses/LICENSE
computer_mcp-0.0.7.dist-info/METADATA
computer_mcp-0.0.7.dist-info/WHEEL
computer_mcp-0.0.7.dist-info/entry_points.txt
computer_mcp-0.0.7.dist-info/top_level.txt
computer_mcp-0.0.7.dist-info/RECORD
