Metadata-Version: 2.4
Name: computer-mcp
Version: 0.0.7
Summary: Cross-platform MCP server for computer automation and control
Author-email: CommandAGI <hello@commandagi.com>
License: MIT
Project-URL: Homepage, https://commandagi.com
Project-URL: Repository, https://github.com/commandAGI/computer-mcp
Project-URL: Issues, https://github.com/commandAGI/computer-mcp/issues
Project-URL: Documentation, https://github.com/commandAGI/computer-mcp#readme
Keywords: mcp,automation,mouse,keyboard,screenshot,accessibility,control
Classifier: Development Status :: 4 - Beta
Classifier: Intended Audience :: Developers
Classifier: License :: OSI Approved :: MIT License
Classifier: Programming Language :: Python :: 3
Classifier: Programming Language :: Python :: 3.12
Classifier: Programming Language :: Python :: 3.13
Classifier: Topic :: Software Development :: Libraries :: Python Modules
Classifier: Topic :: System :: Hardware
Classifier: Operating System :: OS Independent
Requires-Python: >=3.12
License-File: LICENSE
Requires-Dist: mcp>=1.0.0
Requires-Dist: pynput>=1.7.6
Requires-Dist: mss>=9.0.1
Requires-Dist: Pillow>=10.0.0
Requires-Dist: psutil>=5.9.0
Provides-Extra: windows
Requires-Dist: pywin32>=306; extra == "windows"
Provides-Extra: macos
Requires-Dist: pyobjc-framework-Quartz>=10.0; extra == "macos"
Provides-Extra: linux
Requires-Dist: PyGObject>=3.44; extra == "linux"
Provides-Extra: api
Requires-Dist: fastapi>=0.100.0; extra == "api"
Requires-Dist: uvicorn>=0.23.0; extra == "api"
Provides-Extra: http
Requires-Dist: aiohttp>=3.9.0; extra == "http"
Provides-Extra: dev
Requires-Dist: fastapi>=0.100.0; extra == "dev"
Requires-Dist: uvicorn>=0.23.0; extra == "dev"
Requires-Dist: aiohttp>=3.9.0; extra == "dev"
Dynamic: license-file
